{"note":"This file is an internal implementation detail to speed up HTML report generation. Its format can change at any time. You might be looking for the JSON report: https://coverage.rtfd.io/cmd.html#cmd-json","format":5,"version":"7.6.12","globals":"bb158a94a3feefdffe01ad44830d4daa","files":{"z_145eef247bfb46b6___init___py":{"hash":"3c77fc9ef7f887ac2508d4109cf92472","index":{"url":"z_145eef247bfb46b6___init___py.html","file":"src/__init__.py","description":"","nums":{"precision":0,"n_files":1,"n_statements":0,"n_excluded":0,"n_missing":0,"n_branches":0,"n_partial_branches":0,"n_missing_branches":0}}},"z_145eef247bfb46b6_base_class_me_py":{"hash":"f13f795e3785867fa15ece389413e2f1","index":{"url":"z_145eef247bfb46b6_base_class_me_py.html","file":"src/base_class_me.py","description":"","nums":{"precision":0,"n_files":1,"n_statements":1,"n_excluded":4,"n_missing":0,"n_branches":0,"n_partial_branches":0,"n_missing_branches":0}}},"z_145eef247bfb46b6_category_py":{"hash":"82c8e22eb28bc19d95db1c8419c2e8d9","index":{"url":"z_145eef247bfb46b6_category_py.html","file":"src/category.py","description":"","nums":{"precision":0,"n_files":1,"n_statements":47,"n_excluded":3,"n_missing":0,"n_branches":0,"n_partial_branches":0,"n_missing_branches":0}}},"z_663f1908314274f8___init___py":{"hash":"3c77fc9ef7f887ac2508d4109cf92472","index":{"url":"z_663f1908314274f8___init___py.html","file":"src/exception/__init__.py","description":"","nums":{"precision":0,"n_files":1,"n_statements":0,"n_excluded":0,"n_missing":0,"n_branches":0,"n_partial_branches":0,"n_missing_branches":0}}},"z_663f1908314274f8_zero_product_quantity_py":{"hash":"3a4f947222c8692895d22ccd59391fdc","index":{"url":"z_663f1908314274f8_zero_product_quantity_py.html","file":"src/exception/zero_product_quantity.py","description":"","nums":{"precision":0,"n_files":1,"n_statements":6,"n_excluded":0,"n_missing":0,"n_branches":0,"n_partial_branches":0,"n_missing_branches":0}}},"z_145eef247bfb46b6_order_py":{"hash":"64d510049870587b7a484871dffe8051","index":{"url":"z_145eef247bfb46b6_order_py.html","file":"src/order.py","description":"","nums":{"precision":0,"n_files":1,"n_statements":17,"n_excluded":3,"n_missing":0,"n_branches":0,"n_partial_branches":0,"n_missing_branches":0}}},"z_145eef247bfb46b6_print_mixin_py":{"hash":"7e4d6c313da25b00a68600f685f70a3b","index":{"url":"z_145eef247bfb46b6_print_mixin_py.html","file":"src/print_mixin.py","description":"","nums":{"precision":0,"n_files":1,"n_statements":8,"n_excluded":0,"n_missing":0,"n_branches":0,"n_partial_branches":0,"n_missing_branches":0}}},"z_746a184a002e350e___init___py":{"hash":"3c77fc9ef7f887ac2508d4109cf92472","index":{"url":"z_746a184a002e350e___init___py.html","file":"src/product/__init__.py","description":"","nums":{"precision":0,"n_files":1,"n_statements":0,"n_excluded":0,"n_missing":0,"n_branches":0,"n_partial_branches":0,"n_missing_branches":0}}},"z_746a184a002e350e_base_product_py":{"hash":"5bc8dfeac08fbb3481fcf6759324f33e","index":{"url":"z_746a184a002e350e_base_product_py.html","file":"src/product/base_product.py","description":"","nums":{"precision":0,"n_files":1,"n_statements":1,"n_excluded":5,"n_missing":0,"n_branches":0,"n_partial_branches":0,"n_missing_branches":0}}},"z_746a184a002e350e_lawn_grass_py":{"hash":"e2fd22054af370f04509601780217440","index":{"url":"z_746a184a002e350e_lawn_grass_py.html","file":"src/product/lawn_grass.py","description":"","nums":{"precision":0,"n_files":1,"n_statements":9,"n_excluded":1,"n_missing":0,"n_branches":0,"n_partial_branches":0,"n_missing_branches":0}}},"z_746a184a002e350e_product_py":{"hash":"66dd0be3626208b630b07fced496cc67","index":{"url":"z_746a184a002e350e_product_py.html","file":"src/product/product.py","description":"","nums":{"precision":0,"n_files":1,"n_statements":41,"n_excluded":2,"n_missing":0,"n_branches":0,"n_partial_branches":0,"n_missing_branches":0}}},"z_746a184a002e350e_smartphone_py":{"hash":"68d348df4d1633a817be2e658f360204","index":{"url":"z_746a184a002e350e_smartphone_py.html","file":"src/product/smartphone.py","description":"","nums":{"precision":0,"n_files":1,"n_statements":11,"n_excluded":1,"n_missing":0,"n_branches":0,"n_partial_branches":0,"n_missing_branches":0}}}}}